funchain/__init__.py
funchain/_tools.py
funchain/core.py
funchain/py.typed
FunChain-0.1.0.dist-info/LICENSE
FunChain-0.1.0.dist-info/METADATA
FunChain-0.1.0.dist-info/WHEEL
FunChain-0.1.0.dist-info/top_level.txt
FunChain-0.1.0.dist-info/RECORD
