Metadata-Version: 2.1
Name: FunChain
Version: 0.1.0
Summary: Chain functions easily and safely
Author: MARSO Adnan
License: MIT License
Project-URL: repository, https://github.com/mediadnan/funchain
Project-URL: documentation, https://funchain.readthedocs.com
Project-URL: bugs, https://github.com/mediadnan/funchain/issues
Keywords: function,functional,chain,chaining,pipe,compose,composition,processing,safe,handle,report,failure
Classifier: Intended Audience :: Developers
Classifier: Intended Audience :: Science/Research
Classifier: Intended Audience :: Information Technology
Classifier: Operating System :: OS Independent
Classifier: Programming Language :: Python :: 3
Classifier: Programming Language :: Python :: 3 :: Only
Classifier: Programming Language :: Python :: 3.9
Classifier: Programming Language :: Python :: 3.10
Classifier: Programming Language :: Python :: 3.11
Classifier: Programming Language :: Python :: 3.12
Classifier: Topic :: Scientific/Engineering
Classifier: Topic :: Software Development
Classifier: Topic :: Utilities
Classifier: Typing :: Typed
Requires-Python: >=3.9
License-File: LICENSE
Requires-Dist: failures ==1.0.1
